anton/__init__.py
anton/core/__init__.py
anton/core/getter.py
anton/core/loader.py
anton/core/type_handlers/__init__.py
anton/core/type_handlers/constants.py
anton/core/type_handlers/generate_objects.py
anton/core/type_handlers/type_match.py
anton/json.py
anton/yaml.py
anton-0.2.0.dist-info/WHEEL
anton-0.2.0.dist-info/METADATA
anton-0.2.0.dist-info/LICENSE
anton-0.2.0.dist-info/RECORD
